{
  "format_version": "1.12",
  "minecraft:recipe_shaped": {
    "description": {
      "identifier": "cavemen_bat_f44c034a"
    },
    "tags": [
      "crafting_table"
    ],
    "pattern": [
      "  A",
      " B ",
      "C  "
    ],
    "key": {
      "A": {
        "item": "assy:hard_plank",
        "data": 0
      },
      "B": {
        "item": "minecraft:oak_planks",
        "data": 0
      },
      "C": {
        "item": "minecraft:stick",
        "data": 0
      }
    },
    "result": {
      "item": "assy:cavemen_bat",
      "count": 1
    }
  }
}