{
  "format_version": "1.12",
  "minecraft:recipe_shaped": {
    "description": {
      "identifier": "hard_plank_12d71183"
    },
    "tags": [
      "crafting_table"
    ],
    "pattern": [
      "ABA",
      "BCB",
      "ABA"
    ],
    "key": {
      "A": {
        "item": "minecraft:stick",
        "data": 0
      },
      "B": {
        "item": "minecraft:iron_ingot",
        "data": 0
      },
      "C": {
        "item": "minecraft:oak_planks",
        "data": 0
      }
    },
    "result": {
      "item": "assy:hard_plank",
      "count": 1
    }
  }
}